README.rst
setup.py
zuul_get/__init__.py
zuul_get/zuul_get.py
zuul_get.egg-info/PKG-INFO
zuul_get.egg-info/SOURCES.txt
zuul_get.egg-info/dependency_links.txt
zuul_get.egg-info/entry_points.txt
zuul_get.egg-info/pbr.json
zuul_get.egg-info/requires.txt
zuul_get.egg-info/top_level.txt