Metadata-Version: 1.0
Name: zuul-get
Version: 1.1
Summary: Retrieves CI job URLs from OpenStack Zuul
Home-page: https://github.com/major/zuul_get
Author: Major Hayden
Author-email: major@mhtx.net
License: UNKNOWN
Platform: UNKNOWN
